pyfurion/__init__.py
pyfurion/config.py
pyfurion/furion_client.py
pyfurion/meta_bucket.py
pyfurion/meta_path_util.py
pyfurion/snapshot.py
pyfurion/zookeeper.py
pyfurion-0.1.5.dist-info/METADATA
pyfurion-0.1.5.dist-info/WHEEL
pyfurion-0.1.5.dist-info/top_level.txt
pyfurion-0.1.5.dist-info/RECORD
